vpitools/__init__.py
vpitools/EDA/__init__.py
vpitools/EDA/Plotting/__init__.py
vpitools/EDA/Plotting/log_plot.py
vpitools/EDA/Plotting/missing_stats.py
vpitools/EDA/Plotting/view_curves.py
vpitools-0.1.6.dist-info/LICENSE
vpitools-0.1.6.dist-info/METADATA
vpitools-0.1.6.dist-info/WHEEL
vpitools-0.1.6.dist-info/top_level.txt
vpitools-0.1.6.dist-info/RECORD
