Metadata-Version: 2.1
Name: vpitools
Version: 0.1.6
Summary: Update Long Description
Home-page: https://vpi.pvn.vn/
Author: DnA Teams
Author-email: dna.teams@vpi.pvn.vn
License: MIT
Platform: UNKNOWN
License-File: LICENSE
Requires-Dist: seaborn
Requires-Dist: plotly
Requires-Dist: altair
Requires-Dist: numpy
Requires-Dist: matplotlib (==3.4.3)
Requires-Dist: pandas (>=1.4.3)
Requires-Dist: scikit-learn (>=1.1.1)
Requires-Dist: xgboost (>=1.5.1)
Requires-Dist: lightgbm (>=3.3.2)
Requires-Dist: matplotlib (>=3.4.3)
Requires-Dist: shap (>=0.41.0)
Requires-Dist: fasttreeshap (>=0.1.2)
Requires-Dist: scipy (>=1.9.0)
Requires-Dist: mlens (>=0.2.3)
Requires-Dist: omnixai (>=1.1.2)
Requires-Dist: lime (>=0.2.0.1)
Requires-Dist: scikit-optimize
Requires-Dist: imblearn
Requires-Dist: optuna
Requires-Dist: interpret
Requires-Dist: catboost
